LICENSE
MANIFEST.in
README.md
setup.py
pyrfxcom.egg-info/PKG-INFO
pyrfxcom.egg-info/SOURCES.txt
pyrfxcom.egg-info/dependency_links.txt
pyrfxcom.egg-info/top_level.txt
rfxcom/__init__.py
rfxcom/message.py