Metadata-Version: 1.1
Name: pyrfxcom
Version: 0.1.0
Summary: Python library for reading from an rfxcom USB unit
Home-page: http://github.com/barnybug/pyrfxcom/
Author: Barnaby Gray
Author-email: barnaby@pickle.me.uk
License: MIT
Platform: UNKNOWN
Classifier: Development Status :: 3 - Alpha
Classifier: Topic :: Software Development :: Libraries :: Python Modules
Classifier: Intended Audience :: Developers
Classifier: License :: OSI Approved :: MIT License
